MANIFEST.in
readme.md
setup.cfg
setup.py
unrepl/changelog.txt
unrepl/unrepl.py
unrepl.egg-info/PKG-INFO
unrepl.egg-info/SOURCES.txt
unrepl.egg-info/dependency_links.txt
unrepl.egg-info/top_level.txt