Metadata-Version: 2.1
Name: unrepl
Version: 1.0.5.4
Summary: Translates REPL code fragments to proper Python code
Home-page: https://github.com/salabim/unrepl
Author: Ruud van der Ham
Author-email: info@salabim.org
License: UNKNOWN
Download-URL: https://github.com/salabim/unrepl
Keywords: repl
Platform: UNKNOWN
Classifier: Development Status :: 5 - Production/Stable
Classifier: License :: OSI Approved :: MIT License
Classifier: Operating System :: OS Independent
Classifier: Programming Language :: Python :: 3.6
Classifier: Programming Language :: Python :: 3.7
Classifier: Programming Language :: Python :: 3.8
Classifier: Programming Language :: Python :: 3.9
Classifier: Programming Language :: Python :: 3.10
Requires-Python: >=3.6
